CHANGES.txt
COPYRIGHT.txt
LICENSE.txt
bootstrap.py
buildout.cfg
grok-1.0a1.cfg
setup.py
versions.cfg
src/gocept/__init__.py
src/gocept.lms.egg-info/PKG-INFO
src/gocept.lms.egg-info/SOURCES.txt
src/gocept.lms.egg-info/dependency_links.txt
src/gocept.lms.egg-info/entry_points.txt
src/gocept.lms.egg-info/namespace_packages.txt
src/gocept.lms.egg-info/not-zip-safe
src/gocept.lms.egg-info/requires.txt
src/gocept.lms.egg-info/top_level.txt
src/gocept/lms/README.txt
src/gocept/lms/__init__.py
src/gocept/lms/app.py
src/gocept/lms/app.txt
src/gocept/lms/check.py
src/gocept/lms/check.txt
src/gocept/lms/client.py
src/gocept/lms/configure.zcml
src/gocept/lms/filter.py
src/gocept/lms/ftesting.zcml
src/gocept/lms/ftp.py
src/gocept/lms/ftp.txt
src/gocept/lms/handler.py
src/gocept/lms/http.py
src/gocept/lms/http.txt
src/gocept/lms/interfaces.py
src/gocept/lms/mail.py
src/gocept/lms/mailto.py
src/gocept/lms/munin.py
src/gocept/lms/munin.txt
src/gocept/lms/notify.py
src/gocept/lms/notify.txt
src/gocept/lms/runner.py
src/gocept/lms/runner.txt
src/gocept/lms/schedule.py
src/gocept/lms/schedule.txt
src/gocept/lms/sync.py
src/gocept/lms/sync.txt
src/gocept/lms/tests.py
src/gocept/lms/url.py
src/gocept/lms/url.txt
src/gocept/lms/urlhandler.txt
src/gocept/lms/xmlrpc.txt
src/gocept/lms/app_templates/alerts.pt
src/gocept/lms/app_templates/index.pt
src/gocept/lms/app_templates/urls.pt
src/gocept/lms/generations/__init__.py
src/gocept/lms/generations/install.py
src/gocept/lms/scripts/cleanup_db.py
src/gocept/lms/scripts/munin_plugin.py
src/gocept/lms/scripts/reinit_queue.py
src/gocept/lms/static/README.txt