Metadata-Version: 1.0
Name: gocept.lms
Version: 3.0a6
Summary: gocept Link Monitoring Server
Home-page: http://pypi.python.org/pypi/gocept.lms
Author: gocept
Author-email: mail@gocept.com
License: ZPL 2.1
Keywords: zope lms link checking
Platform: UNKNOWN
Classifier: Development Status :: 3 - Alpha
Classifier: Environment :: No Input/Output (Daemon)
Classifier: Framework :: Zope3
Classifier: Framework :: ZODB
Classifier: Intended Audience :: System Administrators
Classifier: License :: OSI Approved :: Zope Public License
Classifier: Natural Language :: English
Classifier: Operating System :: OS Independent
Classifier: Programming Language :: Python
Classifier: Topic :: Internet :: WWW/HTTP :: Site Management :: Link Checking
Classifier: Topic :: System :: Monitoring
